[
  {
    "line": 2,
    "elements": [
      {
        "line": 4,
        "name": "",
        "description": "",
        "type": "background",
        "keyword": "Background",
        "steps": [
          {
            "result": {
              "duration": 1115916800,
              "status": "passed"
            },
            "line": 5,
            "name": "User have to enter facebook through chrome Browser",
            "match": {
              "location": "StepDefintion.user_have_to_enter_facebook_through_chrome_Browser()"
            },
            "keyword": "Given "
          }
        ]
      },
      {
        "start_timestamp": "2022-03-30T16:38:20.561Z",
        "before": [
          {
            "result": {
              "duration": 542100,
              "status": "passed"
            },
            "match": {
              "location": "Hooks.bfr1()"
            }
          },
          {
            "result": {
              "duration": 163500,
              "status": "passed"
            },
            "match": {
              "location": "Hooks.bfr2()"
            }
          },
          {
            "result": {
              "duration": 2930507500,
              "status": "passed"
            },
            "match": {
              "location": "Hooks.bfrScene()"
            }
          }
        ],
        "line": 8,
        "name": "",
        "description": "     To validate login with invalid and valid values",
        "id": "to-validate-login-functionality-of-facebook-application;",
        "after": [
          {
            "result": {
              "duration": 4190327800,
              "status": "passed"
            },
            "match": {
              "location": "Hooks.afrSce(Scenario)"
            }
          },
          {
            "result": {
              "duration": 75400,
              "status": "passed"
            },
            "match": {
              "location": "Hooks.afr2()"
            }
          },
          {
            "result": {
              "duration": 97400,
              "status": "passed"
            },
            "match": {
              "location": "Hooks.afr1()"
            }
          }
        ],
        "type": "scenario",
        "keyword": "Scenario",
        "steps": [
          {
            "result": {
              "duration": 296083100,
              "status": "passed"
            },
            "line": 11,
            "name": "User have to enter invalid email and valid password",
            "match": {
              "location": "StepDefintion.user_have_to_enter_invalid_email_and_valid_password(DataTable)"
            },
            "rows": [
              {
                "cells": [
                  "username",
                  "Gowri"
                ]
              },
              {
                "cells": [
                  "password",
                  "45678"
                ]
              },
              {
                "cells": [
                  "email",
                  "greens@gmail.com"
                ]
              }
            ],
            "keyword": "When "
          },
          {
            "result": {
              "duration": 2143318500,
              "status": "passed"
            },
            "line": 15,
            "name": "User have to click login button",
            "match": {
              "location": "StepDefintion.user_have_to_click_login_button()"
            },
            "keyword": "And "
          },
          {
            "result": {
              "duration": 4120472800,
              "status": "passed"
            },
            "line": 16,
            "name": "user have to show credentials page",
            "match": {
              "location": "StepDefintion.user_have_to_show_credentials_page()"
            },
            "keyword": "Then "
          }
        ],
        "tags": [
          {
            "name": "@regression"
          },
          {
            "name": "@sanity"
          }
        ]
      },
      {
        "line": 4,
        "name": "",
        "description": "",
        "type": "background",
        "keyword": "Background",
        "steps": [
          {
            "result": {
              "duration": 1072275700,
              "status": "passed"
            },
            "line": 5,
            "name": "User have to enter facebook through chrome Browser",
            "match": {
              "location": "StepDefintion.user_have_to_enter_facebook_through_chrome_Browser()"
            },
            "keyword": "Given "
          }
        ]
      },
      {
        "start_timestamp": "2022-03-30T16:38:35.405Z",
        "before": [
          {
            "result": {
              "duration": 161200,
              "status": "passed"
            },
            "match": {
              "location": "Hooks.bfr1()"
            }
          },
          {
            "result": {
              "duration": 108900,
              "status": "passed"
            },
            "match": {
              "location": "Hooks.bfr2()"
            }
          },
          {
            "result": {
              "duration": 1460224800,
              "status": "passed"
            },
            "match": {
              "location": "Hooks.bfrScene()"
            }
          }
        ],
        "line": 19,
        "name": "",
        "description": "    To validate login with valid and valid values",
        "id": "to-validate-login-functionality-of-facebook-application;",
        "after": [
          {
            "result": {
              "duration": 4202964200,
              "status": "passed"
            },
            "match": {
              "location": "Hooks.afrSce(Scenario)"
            }
          },
          {
            "result": {
              "duration": 112900,
              "status": "passed"
            },
            "match": {
              "location": "Hooks.afr2()"
            }
          },
          {
            "result": {
              "duration": 118600,
              "status": "passed"
            },
            "match": {
              "location": "Hooks.afr1()"
            }
          }
        ],
        "type": "scenario",
        "keyword": "Scenario",
        "steps": [
          {
            "result": {
              "duration": 260694500,
              "status": "passed"
            },
            "line": 23,
            "name": "User have to enter valid emailadd and valid password",
            "match": {
              "location": "StepDefintion.user_have_to_enter_valid_emailadd_and_valid_password(DataTable)"
            },
            "rows": [
              {
                "cells": [
                  "UserName",
                  "Email",
                  "Password"
                ]
              },
              {
                "cells": [
                  "Selenium",
                  "GreensTechnology",
                  "12345678"
                ]
              },
              {
                "cells": [
                  "java123",
                  "python",
                  "908734566"
                ]
              },
              {
                "cells": [
                  "manual",
                  "Testing",
                  "Automation"
                ]
              }
            ],
            "keyword": "When "
          },
          {
            "result": {
              "duration": 2114526200,
              "status": "passed"
            },
            "line": 28,
            "name": "User have to click login button",
            "match": {
              "location": "StepDefintion.user_have_to_click_login_button()"
            },
            "keyword": "And "
          },
          {
            "result": {
              "duration": 3743697700,
              "status": "passed"
            },
            "line": 29,
            "name": "user have to show credentials page",
            "match": {
              "location": "StepDefintion.user_have_to_show_credentials_page()"
            },
            "keyword": "Then "
          }
        ],
        "tags": [
          {
            "name": "@regression"
          },
          {
            "name": "@greens"
          }
        ]
      }
    ],
    "name": "To validate Login functionality of Facebook application",
    "description": "",
    "id": "to-validate-login-functionality-of-facebook-application",
    "keyword": "Feature",
    "uri": "file:src/test/resources/FeatureFile/Login.feature",
    "tags": [
      {
        "name": "@regression",
        "type": "Tag",
        "location": {
          "line": 1,
          "column": 1
        }
      }
    ]
  },
  {
    "line": 2,
    "elements": [
      {
        "start_timestamp": "2022-03-30T16:38:48.269Z",
        "before": [
          {
            "result": {
              "duration": 218000,
              "status": "passed"
            },
            "match": {
              "location": "Hooks.bfr1()"
            }
          },
          {
            "result": {
              "duration": 123300,
              "status": "passed"
            },
            "match": {
              "location": "Hooks.bfr2()"
            }
          },
          {
            "result": {
              "duration": 1459834600,
              "status": "passed"
            },
            "match": {
              "location": "Hooks.bfrScene()"
            }
          }
        ],
        "line": 5,
        "name": "To validate forget password",
        "description": "",
        "id": "to-validate-forgot-password-functionality-of-facebook-application;to-validate-forget-password",
        "after": [
          {
            "result": {
              "duration": 4200586000,
              "status": "passed"
            },
            "match": {
              "location": "Hooks.afrSce(Scenario)"
            }
          },
          {
            "result": {
              "duration": 111900,
              "status": "passed"
            },
            "match": {
              "location": "Hooks.afr2()"
            }
          },
          {
            "result": {
              "duration": 36300,
              "status": "passed"
            },
            "match": {
              "location": "Hooks.afr1()"
            }
          }
        ],
        "type": "scenario",
        "keyword": "Scenario",
        "steps": [
          {
            "result": {
              "duration": 1072233600,
              "status": "passed"
            },
            "line": 6,
            "name": "User have to enter facebook through chrome Browser",
            "match": {
              "location": "StepDefintion.user_have_to_enter_facebook_through_chrome_Browser()"
            },
            "keyword": "Given "
          },
          {
            "result": {
              "duration": 1143685000,
              "status": "passed"
            },
            "line": 7,
            "name": "user have to click forgot password",
            "match": {
              "location": "StepDefintion.user_have_to_click_forgot_password()"
            },
            "keyword": "And "
          },
          {
            "result": {
              "duration": 84066400,
              "status": "passed"
            },
            "line": 8,
            "name": "user have to enter email or phone number",
            "match": {
              "location": "StepDefintion.user_have_to_enter_email_or_phone_number()"
            },
            "keyword": "When "
          },
          {
            "result": {
              "duration": 2113006600,
              "status": "passed"
            },
            "line": 9,
            "name": "User have to click login button",
            "match": {
              "location": "StepDefintion.user_have_to_click_login_button()"
            },
            "keyword": "And "
          },
          {
            "result": {
              "duration": 7480600,
              "status": "passed"
            },
            "line": 10,
            "name": "user have to show credentials page",
            "match": {
              "location": "StepDefintion.user_have_to_show_credentials_page()"
            },
            "keyword": "Then "
          }
        ],
        "tags": [
          {
            "name": "@smoke"
          },
          {
            "name": "@greens"
          }
        ]
      }
    ],
    "name": "To validate Forgot Password functionality of Facebook application",
    "description": "",
    "id": "to-validate-forgot-password-functionality-of-facebook-application",
    "keyword": "Feature",
    "uri": "file:src/test/resources/FeatureFile/frgtPassword.feature",
    "tags": [
      {
        "name": "@smoke",
        "type": "Tag",
        "location": {
          "line": 1,
          "column": 1
        }
      }
    ]
  }
]